auth/BearerAuth.py
auth/__init__.py
cli/__init__.py
cli/__main__.py
cli/links.py
cli/prediction.py
cli/tlcli.py
xml_report/__init__.py
xml_report/link_prediction_example.py
xml_report/xml_processor.py
tracelynx_cli-0.1.18.dist-info/METADATA
tracelynx_cli-0.1.18.dist-info/WHEEL
tracelynx_cli-0.1.18.dist-info/entry_points.txt
tracelynx_cli-0.1.18.dist-info/top_level.txt
tracelynx_cli-0.1.18.dist-info/RECORD
