Metadata-Version: 2.1
Name: tracelynx-cli
Version: 0.1.18
Summary: The TraceLynx CLI tool for processing the xml generated in the test execution to generate the xml for the predicted links
Author-email: TraceLynx <axel.reichwein@koneksys.com>
Maintainer-email: TraceLynx <axel.reichwein@koneksys.com>
Classifier: Programming Language :: Python :: 3.12
Requires-Python: >=3.12
Requires-Dist: click
Requires-Dist: httpx
